cognee_integration_langgraph/__init__.py
cognee_integration_langgraph/bootstrap.py
cognee_integration_langgraph/tools.py
cognee_integration_langgraph-0.1.7.dist-info/METADATA
cognee_integration_langgraph-0.1.7.dist-info/WHEEL
cognee_integration_langgraph-0.1.7.dist-info/top_level.txt
cognee_integration_langgraph-0.1.7.dist-info/RECORD
