Metadata-Version: 2.4
Name: cognee-integration-langgraph
Version: 0.1.7
Summary: A powerful integration between LangGraph and Cognee providing intelligent knowledge management and retrieval capabilities for AI agents
Author: Cognee team
Project-URL: Homepage, https://github.com/topoteretes/cognee-integration-langgraph
Project-URL: Repository, https://github.com/topoteretes/cognee-integration-langgraph
Project-URL: Documentation, https://github.com/topoteretes/cognee-integration-langgraph#readme
Requires-Python: >=3.10
Requires-Dist: cognee>=0.5.1
Requires-Dist: grandalf>=0.8
Requires-Dist: ipykernel>=6.30.1
Requires-Dist: ipython>=8.10.0
Requires-Dist: langchain
Requires-Dist: langchain-community>=0.3.29
Requires-Dist: langchain_openai
Requires-Dist: langgraph
Requires-Dist: neo4j>=6.1.0
Requires-Dist: python-dotenv
